Metadata-Version: 2.1
Name: novigi-airflow-customs
Version: 1.0.6
Summary: Novigi Custom Airflow operators, hooks and plugins
Home-page: UNKNOWN
Author: Novigi
Author-email: integration@novigi.com.au
License: MIT
Platform: UNKNOWN
License-File: LICENSE.txt
